flask_commonmark.py
Flask_Commonmark-1.0.4.dist-info/LICENSE
Flask_Commonmark-1.0.4.dist-info/METADATA
Flask_Commonmark-1.0.4.dist-info/WHEEL
Flask_Commonmark-1.0.4.dist-info/top_level.txt
Flask_Commonmark-1.0.4.dist-info/RECORD
