Metadata-Version: 2.1
Name: Flask-Commonmark
Version: 1.0.4
Summary: Add commonmark processing filter to your Flask app.
Home-page: https://gitlab.com/doug.shawhan/flask-commonmark
Author: Doug Shawhan
Author-email: doug.shawhan@gmail.com
Maintainer: Doug Shawhan
Maintainer-email: doug.shawhan@gmail.com
License: Copyright 2019 Doug Shawhan        
Project-URL: Bug Tracker, https://gitlab.com/doug.shawhan/flask-commonmark/issues
Project-URL: Source Code, https://gitlab.com/doug.shawhan/flask-commonmark/tree/master
Project-URL: Development Version, https://gitlab.com/doug.shawhan/flask-commonmark/tree/dev
Project-URL: Documentation, https://flask-commonmark.readthedocs.io
Platform: any
Classifier: Development Status :: 5 - Production/Stable
Classifier: Environment :: Web Environment
Classifier: Framework :: Flask
Classifier: Intended Audience :: Developers
Classifier: License :: OSI Approved :: BSD License
Classifier: Operating System :: OS Independent
Classifier: Programming Language :: Python
Classifier: Programming Language :: Python :: 3.6
Classifier: Programming Language :: Python :: 3.7
Classifier: Programming Language :: Python :: 3.8
Classifier: Programming Language :: Python :: 3.9
Classifier: Topic :: Internet :: WWW/HTTP :: Dynamic Content
Classifier: Topic :: Software Development :: Libraries :: Python Modules
License-File: LICENSE
Requires-Dist: Flask
Requires-Dist: commonmark
Requires-Dist: jinja2 (>=3)
Requires-Dist: markupsafe (>=2)
